pycaptchagen/__init__.py
pycaptchagen/__main__.py
pycaptchagen/pycaptchagen.py
pycaptchagen-0.1.0.data/data/LICENSE
pycaptchagen-0.1.0.data/scripts/pycaptchagen
pycaptchagen-0.1.0.dist-info/LICENSE
pycaptchagen-0.1.0.dist-info/METADATA
pycaptchagen-0.1.0.dist-info/WHEEL
pycaptchagen-0.1.0.dist-info/top_level.txt
pycaptchagen-0.1.0.dist-info/RECORD
