Metadata-Version: 2.1
Name: pycaptchagen
Version: 0.1.0
Summary: Generate once-off "CAPTCHA"-type images and audio files from the command line.
Home-page: UNKNOWN
Author: Christopher Hackmeyer
Author-email: cbhackmeyer@allisforall.dedyn.io
License: The Unlicense (Public Domain)
Platform: UNKNOWN
Classifier: Programming Language :: Python :: 3
Classifier: License :: Public Domain
Classifier: Operating System :: OS Independent
Requires-Python: ~=3.2
Requires-Dist: captcha
